ratan/counter/counter.v
module counter(input clk,input reset,input enable,input up_down,output reg[3:0] count);
always @(posedge clk) begin
	if(reset)
		count<=4'b0000;
	else if(enable) begin
		if(up_down)
			count<=count+1'b1;
		else
			count<=count-1'b1;
	end
end
endmodule

ratan/counter/counter_tb.v
module counter_tb;
reg clk;
reg reset;
reg enable;
reg up_down;
wire [3:0] count;
counter DUT(.clk(clk), .reset(reset), .enable(enable), .up_down(up_down), .count(count));
always #5 clk=~clk;
initial begin
	$dumpfile("counter.vcd");
	$dumpvars(0,counter_tb);
	$monitor("Time=%0t | Reset=%b Enable=%b Up_Down=%b |Count=%d",$time,reset,enable,up_down,count);
	clk=0;
	reset=1;
	enable=0;
	up_down=1;
	#10 reset=0;
	enable=1;
	up_down=1;
	#80 up_down=0;
	#50 enable=0;
	#20 reset=1;
	#10 $finish;
end
endmodule

ratan/counter/counter.vcd
$date
	Fri Aug 28 11:23:31 2026
$end
$version
	Icarus Verilog
$end
$timescale
	1s
$end
$scope module counter_tb $end
$var wire 4 ! count [3:0] $end
$var reg 1 " clk $end
$var reg 1 # enable $end
$var reg 1 $ reset $end
$var reg 1 % up_down $end
$scope module DUT $end
$var wire 1 " clk $end
$var wire 1 # enable $end
$var wire 1 $ reset $end
$var wire 1 % up_down $end
$var reg 4 & count [3:0] $end
$upscope $end
$upscope $end
$enddefinitions $end
$comment Show the parameter values. $end
$dumpall
$end
#0
$dumpvars
bx &
1%
1$
0#
0"
bx !
$end
#5
b0 !
b0 &
1"
#10
0"
1#
0$
#15
b1 !
b1 &
1"
#20
0"
#25
b10 !
b10 &
1"
#30
0"
#35
b11 !
b11 &
1"
#40
0"
#45
b100 !
b100 &
1"
#50
0"
#55
b101 !
b101 &
1"
#60
0"
#65
b110 !
b110 &
1"
#70
0"
#75
b111 !
b111 &
1"
#80
0"
#85
b1000 !
b1000 &
1"
#90
0"
0%
#95
b111 !
b111 &
1"
#100
0"
#105
b110 !
b110 &
1"
#110
0"
#115
b101 !
b101 &
1"
#120
0"
#125
b100 !
b100 &
1"
#130
0"
#135
b11 !
b11 &
1"
#140
0"
0#
#145
1"
#150
0"
#155
1"
#160
0"
1$
#165
b0 !
b0 &
1"
