harshi/add.v
module full_adder(
     input a,
     input b,
     input cin,
     output sum,
     output cout
);

assign sum = a ^ b ^ cin;
assign cout = (a & b) | (b & cin) | (a & cin);

endmodule

harshi/add_tb.v
module tb_full_adder;

reg a, b, cin;
wire sum, cout;

full_adder uut(
       .a(a),
       .b(b),
       .cin(cin),
       .sum(sum),
       .cout(cout)
);

initial begin
  $dumpfile("dump.vcd");
  $dumpvars(0, tb_full_adder);

  a=0; b=0; cin=0;
#10 a=0; b=0; cin=1;
#10 a=0; b=1; cin=0;
#10 a=0; b=1; cin=1;
#10 a=1; b=0; cin=0;
#10 a=1; b=0; cin=1;
#10 a=1; b=1; cin=0;
#10 a=1; b=1; cin=1;

#10 $finish;
end
endmodule

harshi/dump.vcd
$date
	Thu Aug 27 07:13:29 2026
$end
$version
	Icarus Verilog
$end
$timescale
	1s
$end
$scope module tb_full_adder $end
$var wire 1 ! sum $end
$var wire 1 " cout $end
$var reg 1 # a $end
$var reg 1 $ b $end
$var reg 1 % cin $end
$scope module uut $end
$var wire 1 # a $end
$var wire 1 $ b $end
$var wire 1 % cin $end
$var wire 1 " cout $end
$var wire 1 ! sum $end
$upscope $end
$upscope $end
$enddefinitions $end
$comment Show the parameter values. $end
$dumpall
$end
#0
$dumpvars
0%
0$
0#
0"
0!
$end
#10
1!
1%
#20
0%
1$
#30
1"
0!
1%
#40
0"
1!
0%
0$
1#
#50
1"
0!
1%
#60
0%
1$
#70
1!
1%
