harshi/ring_osci.v
`timescale 1ns/1ps

module ring_osci(
     output reg n1,
     output reg n2,
     output reg n3
);

initial begin
    n1 = 0;
    n2 = 1;
    n3 = 0;
end

always #1 n1 = ~n3;
always #1 n2 = ~n1;
always #1 n3 = ~n2;

endmodule

harshi/tb_ring_osci.v
`timescale 1ns/1ps

module tb_ring_osci;

wire n1, n2, n3;

ring_osci uut(
   .n1(n1),
   .n2(n2),
   .n3(n3)
);

initial begin
     $dumpfile("ring_osci.vcd");
     $dumpvars(0, tb_ring_osci);

     $monitor("Time=%0t n1=%b n2=%b n3=%b",
              $time, n1, n2, n3);
     #50;
     $finish;
end

endmodule

harshi/ring_osci.vcd
$date
	Fri Aug 28 09:03:04 2026
$end
$version
	Icarus Verilog
$end
$timescale
	1ps
$end
$scope module tb_ring_osci $end
$var wire 1 ! n3 $end
$var wire 1 " n2 $end
$var wire 1 # n1 $end
$scope module uut $end
$var reg 1 # n1 $end
$var reg 1 " n2 $end
$var reg 1 ! n3 $end
$upscope $end
$upscope $end
$enddefinitions $end
$comment Show the parameter values. $end
$dumpall
$end
#0
$dumpvars
0#
1"
0!
$end
#1000
1!
0"
1#
#2000
0!
1"
0#
#3000
1!
0"
1#
#4000
0!
1"
0#
#5000
1!
0"
1#
#6000
0!
1"
0#
#7000
1!
0"
1#
#8000
0!
1"
0#
#9000
1!
0"
1#
#10000
0!
1"
0#
#11000
1!
0"
1#
#12000
0!
1"
0#
#13000
1!
0"
1#
#14000
0!
1"
0#
#15000
1!
0"
1#
#16000
0!
1"
0#
#17000
1!
0"
1#
#18000
0!
1"
0#
#19000
1!
0"
1#
#20000
0!
1"
0#
#21000
1!
0"
1#
#22000
0!
1"
0#
#23000
1!
0"
1#
#24000
0!
1"
0#
#25000
1!
0"
1#
#26000
0!
1"
0#
#27000
1!
0"
1#
#28000
0!
1"
0#
#29000
1!
0"
1#
#30000
0!
1"
0#
#31000
1!
0"
1#
#32000
0!
1"
0#
#33000
1!
0"
1#
#34000
0!
1"
0#
#35000
1!
0"
1#
#36000
0!
1"
0#
#37000
1!
0"
1#
#38000
0!
1"
0#
#39000
1!
0"
1#
#40000
0!
1"
0#
#41000
1!
0"
1#
#42000
0!
1"
0#
#43000
1!
0"
1#
#44000
0!
1"
0#
#45000
1!
0"
1#
#46000
0!
1"
0#
#47000
1!
0"
1#
#48000
0!
1"
0#
#49000
1!
0"
1#
#50000
0!
1"
0#
