harshi/ring_oscillator.v
`timescale 1ns/1ps

module ring_oscillator(
     output n1,
     output n2,
     output n3
);

not #(1) G1(n1, n3);
not #(1) G2(n2, n1);
not #(1) G3(n3, n2);

endmodule

harshi/tb_ring_oscillator.v
`timescale 1ns/1ps

module tb_ring_oscillator;

wire n1,n2,n3;

ring_oscillator uut(
   .n1(n1),
   .n2(n2),
   .n3(n3)
);

initial begin
   $dumpfile("ring_oscillator.vcd");
   $dumpvars(0, tb_ring_oscillator);

   force n1 = 1'b0;
   #2;
   release n1;

   #48;
   $finish;
end

initial begin
   $monitor("Time = %0t ns: n1 = %b  n2 = %b  n3 = %b",
            $time, n1, n2, n3);

  
end

endmodule

harshi/ring_oscillator.vcd
$date
	Fri Aug 28 08:42:19 2026
$end
$version
	Icarus Verilog
$end
$timescale
	1ps
$end
$scope module tb_ring_oscillator $end
$var wire 1 ! n3 $end
$var wire 1 " n2 $end
$var wire 1 # n1 $end
$scope module uut $end
$var wire 1 # n1 $end
$var wire 1 " n2 $end
$var wire 1 ! n3 $end
$upscope $end
$upscope $end
$enddefinitions $end
$comment Show the parameter values. $end
$dumpall
$end
#0
$dumpvars
0#
x"
x!
$end
#1000
1"
#2000
0!
x#
#3000
1#
x"
#4000
0"
x!
#5000
1!
x#
#6000
0#
x"
#7000
1"
x!
#8000
0!
x#
#9000
1#
x"
#10000
0"
x!
#11000
1!
x#
#12000
0#
x"
#13000
1"
x!
#14000
0!
x#
#15000
1#
x"
#16000
0"
x!
#17000
1!
x#
#18000
0#
x"
#19000
1"
x!
#20000
0!
x#
#21000
1#
x"
#22000
0"
x!
#23000
1!
x#
#24000
0#
x"
#25000
1"
x!
#26000
0!
x#
#27000
1#
x"
#28000
0"
x!
#29000
1!
x#
#30000
0#
x"
#31000
1"
x!
#32000
0!
x#
#33000
1#
x"
#34000
0"
x!
#35000
1!
x#
#36000
0#
x"
#37000
1"
x!
#38000
0!
x#
#39000
1#
x"
#40000
0"
x!
#41000
1!
x#
#42000
0#
x"
#43000
1"
x!
#44000
0!
x#
#45000
1#
x"
#46000
0"
x!
#47000
1!
x#
#48000
0#
x"
#49000
1"
x!
#50000
0!
x#
