harshi/subb.v
module full_subtractor(
     input a,
     input b,
     input bin,
     output d,
     output bout
);

assign d = a ^ b ^ bin;
assign bout = (~a & b) | (~a & bin) | (b & bin);

endmodule

harshi/subt_tb.v
module subt_tb;
reg a,b,bin;
wire d,bout;
full_subtractor uut(.a(a),
.b(b),
.bin(bin),
.d(d),
.bout(bout)
);

initial begin
$dumpfile("subt.vcd");
$dumpvars(0,subt_tb);

a=0;b=0;bin=0;
#10 a=0;b=0;bin=1;
#10 a=0;b=1;bin=0;
#10 a=0;b=1;bin=1;
#10 a=1;b=0;bin=0;
#10 a=1;b=0;bin=1;
#10 a=1;b=1;bin=0;
#10 a=1;b=1;bin=1;

#10 $finish;
end

initial begin
$monitor("a=%b b=%b bin=%b | d=%b bout=%b",
a,b,bin,d,bout);
end
endmodule

harshi/subt.vcd
$date
	Tue Aug 25 08:42:19 2026
$end
$version
	Icarus Verilog
$end
$timescale
	1s
$end
$scope module subt_tb $end
$var wire 1 ! d $end
$var wire 1 " bout $end
$var reg 1 # a $end
$var reg 1 $ b $end
$var reg 1 % bin $end
$scope module uut $end
$var wire 1 # a $end
$var wire 1 $ b $end
$var wire 1 % bin $end
$var wire 1 " bout $end
$var wire 1 ! d $end
$upscope $end
$upscope $end
$enddefinitions $end
$comment Show the parameter values. $end
$dumpall
$end
#0
$dumpvars
0%
0$
0#
0"
0!
$end
#10
1"
1!
1%
#20
0%
1$
#30
0!
1%
#40
0"
1!
0%
0$
1#
#50
0!
1%
#60
0%
1$
#70
1"
1!
1%
