karunakara/mux/mux.v
module mux8to1(input[7:0] I,input[2:0] S,output Y);
assign Y=I[S];
endmodule

karunakara/mux/mux_tb.v
module mux8to1_tb;
reg[7:0] I;
reg[2:0] S;
wire Y;
mux8to1 uut(.I(I), .S(S), .Y(Y));
initial begin
 
	$dumpfile("mux8to1.vcd");
	$dumpvars(0,mux8to1_tb);
	I=8'b10101010;
	S=3'b000;
	#10;
	S=3'b001;
	#10;
	S=3'b010;
	#10;
        S=3'b011;
        #10;
        S=3'b100;
	#10;
        S=3'b101;
        #10;
        S=3'b110;
	#10;
        S=3'b111;
        #10;
        $finish;
end
endmodule

karunakara/mux/mux8to1.vcd
$date
	Wed Aug 26 10:40:45 2026
$end
$version
	Icarus Verilog
$end
$timescale
	1s
$end
$scope module mux8to1_tb $end
$var wire 1 ! Y $end
$var reg 8 " I [7:0] $end
$var reg 3 # S [2:0] $end
$scope module uut $end
$var wire 8 $ I [7:0] $end
$var wire 3 % S [2:0] $end
$var wire 1 ! Y $end
$upscope $end
$upscope $end
$enddefinitions $end
$comment Show the parameter values. $end
$dumpall
$end
#0
$dumpvars
b0 %
b10101010 $
b0 #
b10101010 "
0!
$end
#10
1!
b1 #
b1 %
#20
0!
b10 #
b10 %
#30
1!
b11 #
b11 %
#40
0!
b100 #
b100 %
#50
1!
b101 #
b101 %
#60
0!
b110 #
b110 %
#70
1!
b111 #
b111 %
