shailesh/dff.v
module dff (
    input D,
    input CLK,
    output reg Q
);

always @(posedge CLK)
    Q <= D;
endmodule

shailesh/dff_tb.v
module dff_tb;
reg D, CLK;
wire Q;
dff uut (
    .D(D),
    .CLK(CLK),
    .Q(Q)
);

always #5 CLK = ~CLK;

initial begin
    $dumpfile("dff.vcd");
    $dumpvars(0, dff_tb);

    CLK = 0;
    D = 0;

    #10 D = 1;
    #10 D = 0;
    #10 D = 1;
    #10 D = 0;
    #10 $finish;
end
endmodule

dff.vcd
$date
	Thu Aug 27 07:24:42 2026
$end
$version
	Icarus Verilog
$end
$timescale
	1s
$end
$scope module dff_tb $end
$var wire 1 ! Q $end
$var reg 1 " CLK $end
$var reg 1 # D $end
$scope module uut $end
$var wire 1 " CLK $end
$var wire 1 # D $end
$var reg 1 ! Q $end
$upscope $end
$upscope $end
$enddefinitions $end
$comment Show the parameter values. $end
$dumpall
$end
#0
$dumpvars
0#
0"
x!
$end
#5
0!
1"
#10
0"
1#
#15
1!
1"
#20
0"
0#
#25
0!
1"
#30
0"
1#
#35
1!
1"
#40
0"
0#
#45
0!
1"
