vinutha/chaser.v
module led_chaser(
 input clk,
 input reset,
 output reg[3:0]leds
);

always @(posedge clk or posedge reset)begin
 if (reset)begin
  leds<=4'b0001;
 end else begin
  leds<={leds[2:0],leds[3]};
 end
end

endmodule

vinutha/tb_ledchaser.v
module tb_ledchaser;

reg clk;
reg reset;
wire [3:0]leds;

led_chaser uut(
 .clk(clk),
 .reset(reset),
 .leds(leds)
);

always #5 clk=~clk;

initial begin
 clk=0;
 reset=1;
$dumpfile("chaser.vcd");
$dumpvars(0,tb_ledchaser);

 $monitor("time=%3d ns | reset=%b | leds: [%b %b %b%b]",
$time,reset,leds[3],leds[2],leds[1],leds[0]);

 #12 reset=0;
 #80 $finish;

end

endmodule

vinutha/chaser.vcd
$date
	Wed Aug 26 09:39:25 2026
$end
$version
	Icarus Verilog
$end
$timescale
	1s
$end
$scope module tb_ledchaser $end
$var wire 4 ! leds [3:0] $end
$var reg 1 " clk $end
$var reg 1 # reset $end
$scope module uut $end
$var wire 1 " clk $end
$var wire 1 # reset $end
$var reg 4 $ leds [3:0] $end
$upscope $end
$upscope $end
$enddefinitions $end
$comment Show the parameter values. $end
$dumpall
$end
#0
$dumpvars
b1 $
1#
0"
b1 !
$end
#5
1"
#10
0"
#12
0#
#15
b10 !
b10 $
1"
#20
0"
#25
b100 !
b100 $
1"
#30
0"
#35
b1000 !
b1000 $
1"
#40
0"
#45
b1 !
b1 $
1"
#50
0"
#55
b10 !
b10 $
1"
#60
0"
#65
b100 !
b100 $
1"
#70
0"
#75
b1000 !
b1000 $
1"
#80
0"
#85
b1 !
b1 $
1"
