karunakara/i2c_master_project/i2c_master.v
module i2c_master #(parameter CLK_DIV = 4
)(
input wire clk,input wire rst_n,input wire start_i,
input wire [6:0] slave_addr,input wire rw,output reg scl,inout wire sda,
output reg busy,output reg done);

localparam IDLE = 3'd0,START = 3'd1,SHIFT = 3'd2,ACK = 3'd3,STOP = 3'd4,
FIN = 3'd5;

reg [2:0] state;
reg [3:0] bit_idx;
reg [7:0] shift_reg;
reg       sda_out;
reg	  sda_oe;
integer half_cnt;

assign sda = sda_oe ? sda_out : 1'bz;

always @(posedge clk or negedge rst_n) begin
if (!rst_n) begin
state <= IDLE;
scl <= 1'b1;
sda_out <= 1'b1;
sda_oe <= 1'b1;
half_cnt <= 0;
bit_idx <= 4'd0;
shift_reg <= 8'h00;
busy <= 1'b0;
done <= 1'b0;
end else begin
done <= 1'b0;

case (state)
IDLE: begin
scl <= 1'b1;
sda_out <= 1'b1;
sda_oe <= 1'b1;
half_cnt <= 0;

if (start_i) begin
busy <= 1'b1;
shift_reg <= {slave_addr, rw};
bit_idx <= 4'd7;
state <= START;
end
end

START: begin
if (half_cnt == 0)
sda_out <= 1'b0;

if (half_cnt == CLK_DIV-1) begin
half_cnt <= 0;
scl <= 1'b0;
state <= SHIFT;
end else
half_cnt <= half_cnt + 1;
end

SHIFT: begin
if (half_cnt == 0) begin
sda_out <= shift_reg[bit_idx];
scl <= 1'b0;
end

if (half_cnt == CLK_DIV)
scl <= 1'b1;

if (half_cnt == 2*CLK_DIV-1) begin
half_cnt <= 0;
if (bit_idx == 0)
state <= ACK;
else
bit_idx <= bit_idx - 1'b1;
end else
half_cnt <= half_cnt + 1;
end

ACK: begin
if (half_cnt == 0) begin
sda_oe <= 1'b0;
scl <= 1'b0;
end

if (half_cnt == CLK_DIV)
scl <= 1'b1;

if (half_cnt == 2*CLK_DIV-1) begin
half_cnt <= 0;
sda_oe <= 1'b1;
sda_out <= 1'b0;
scl <= 1'b0;
state <= STOP;
end else
half_cnt <= half_cnt + 1;
end



STOP: begin
if (half_cnt == 0) begin
sda_out <= 1'b0;
scl <= 1'b0;
end

if (half_cnt == CLK_DIV)
scl <= 1'b0;

if (half_cnt == CLK_DIV + CLK_DIV/2)
sda_out <= 1'b1;


if (half_cnt == 2*CLK_DIV-1) begin
half_cnt <= 0;
state <= FIN;
end else

half_cnt <= half_cnt + 1;

end

FIN: begin
busy <= 1'b0;
done <= 1'b1;
state <= IDLE;
end
default: state <= IDLE;
endcase
end
end
endmodule

karunakara/i2c_master_project/tb/i2c_master_tb.v
module i2c_master_tb;
localparam CLK_DIV = 4;
reg clk;
reg rst_n;
reg start_i;
reg [6:0] slave_addr;
reg rw;
wire scl;
wire sda;
wire busy;
wire done;

reg slave_ack_drive;
assign sda = slave_ack_drive ? 1'b0 : 1'bz;

pullup (sda);

i2c_master #(.CLK_DIV(CLK_DIV)) DUT (
.clk (clk), .rst_n (rst_n), .start_i (start_i), 
.slave_addr (slave_addr), .rw (rw), .scl (scl), .sda (sda), 
.busy (busy), .done(done));
always #5 clk = ~clk;
reg [7:0] captured;
integer bitcnt;
reg start_seen, stop_seen, ack_sent;

initial begin
clk = 1'b0;
rst_n = 1'b0;
start_i = 1'b0;
slave_addr = 7'h55;
rw = 1'b0;
slave_ack_drive = 1'b0;
captured = 8'h00;
bitcnt = 0;
start_seen = 1'b0;
stop_seen = 1'b0;
ack_sent = 1'b0;

#20 rst_n = 1'b1;
#20 start_i = 1'b1;
#20 start_i = 1'b0;
end

always @(negedge sda)
if (scl) begin 
start_seen = 1'b1;
$display("[%0t ns] START condition detected (SDA fell while SCL high)", $time);
end

always @(posedge sda)
if (scl) begin
stop_seen = 1'b1; 
$display("[%0t ns] STOP condition detected (SDA rose while SCL high)", $time);
end

always @(posedge scl) begin
if (start_seen && bitcnt < 8) begin
captured = {captured[6:0], sda};
bitcnt = bitcnt + 1;
$display("[%0t ns] Sampled bit %0d -> sda = %b", 
$time, bitcnt, sda);
end 
end

always @(negedge scl) begin
if (bitcnt == 8 && !ack_sent) begin
slave_ack_drive <= 1'b1;
ack_sent <= 1'b1;

end else if (ack_sent) begin
slave_ack_drive <= 1'b0;
end
end

initial begin
$dumpfile("i2c_master_tb.vcd");
$dumpvars(0, i2c_master_tb);
end

initial begin 
#2000;
if (start_seen && stop_seen && (captured == {slave_addr,rw}))
$display("\nTest PASSED : captured addr+rw = %b, expected = %b", 
captured, {slave_addr, rw});
else
$display("\nTest FAILED : captured addr+rw = %b, expected = %b, start_seen=%b, stop_seen=%b", captured, 
{slave_addr, rw}, start_seen, stop_seen);
$finish;
end
endmodule

karunakara/i2c_master_project/i2c_master_tb.vcd
$date
	Wed Sep  2 08:11:00 2026
$end
$version
	Icarus Verilog
$end
$timescale
	1s
$end
$scope module i2c_master_tb $end
$var wire 1 ! sda $end
$var wire 1 " scl $end
$var wire 1 # done $end
$var wire 1 $ busy $end
$var parameter 32 % CLK_DIV $end
$var reg 1 & ack_sent $end
$var reg 8 ' captured [7:0] $end
$var reg 1 ( clk $end
$var reg 1 ) rst_n $end
$var reg 1 * rw $end
$var reg 1 + slave_ack_drive $end
$var reg 7 , slave_addr [6:0] $end
$var reg 1 - start_i $end
$var reg 1 . start_seen $end
$var reg 1 / stop_seen $end
$var integer 32 0 bitcnt [31:0] $end
$scope module DUT $end
$var wire 1 ( clk $end
$var wire 1 ) rst_n $end
$var wire 1 * rw $end
$var wire 1 ! sda $end
$var wire 7 1 slave_addr [6:0] $end
$var wire 1 - start_i $end
$var parameter 3 2 ACK $end
$var parameter 32 3 CLK_DIV $end
$var parameter 3 4 FIN $end
$var parameter 3 5 IDLE $end
$var parameter 3 6 SHIFT $end
$var parameter 3 7 START $end
$var parameter 3 8 STOP $end
$var reg 4 9 bit_idx [3:0] $end
$var reg 1 $ busy $end
$var reg 1 # done $end
$var reg 1 " scl $end
$var reg 1 : sda_oe $end
$var reg 1 ; sda_out $end
$var reg 8 < shift_reg [7:0] $end
$var reg 3 = state [2:0] $end
$var integer 32 > half_cnt [31:0] $end
$upscope $end
$upscope $end
$enddefinitions $end
$comment Show the parameter values. $end
$dumpall
b100 8
b1 7
b10 6
b0 5
b101 4
b100 3
b11 2
b100 %
$end
#0
$dumpvars
b0 >
b0 =
b0 <
1;
1:
b0 9
b1010101 1
b0 0
1/
0.
0-
b1010101 ,
0+
0*
0)
0(
b0 '
0&
0$
0#
1"
1!
$end
#5
1(
#10
0(
#15
1(
#20
0(
1)
#25
1(
#30
0(
#35
1(
#40
0(
1-
#45
b1 =
b111 9
b10101010 <
1$
1(
#50
0(
#55
1.
0!
b1 >
0;
1(
#60
0(
0-
#65
b10 >
1(
#70
0(
#75
b11 >
1(
#80
0(
#85
b10 =
0"
b0 >
1(
#90
0(
#95
1!
b1 >
1;
1(
#100
0(
#105
b10 >
1(
#110
0(
#115
b11 >
1(
#120
0(
#125
b100 >
1(
#130
0(
#135
b1 0
b1 '
b101 >
1"
1(
#140
0(
#145
b110 >
1(
#150
0(
#155
b111 >
1(
#160
0(
#165
b110 9
b0 >
1(
#170
0(
#175
0!
b1 >
0"
0;
1(
#180
0(
#185
b10 >
1(
#190
0(
#195
b11 >
1(
#200
0(
#205
b100 >
1(
#210
0(
#215
b10 0
b10 '
b101 >
1"
1(
#220
0(
#225
b110 >
1(
#230
0(
#235
b111 >
1(
#240
0(
#245
b101 9
b0 >
1(
#250
0(
#255
1!
b1 >
0"
1;
1(
#260
0(
#265
b10 >
1(
#270
0(
#275
b11 >
1(
#280
0(
#285
b100 >
1(
#290
0(
#295
b11 0
b101 '
b101 >
1"
1(
#300
0(
#305
b110 >
1(
#310
0(
#315
b111 >
1(
#320
0(
#325
b100 9
b0 >
1(
#330
0(
#335
0!
b1 >
0"
0;
1(
#340
0(
#345
b10 >
1(
#350
0(
#355
b11 >
1(
#360
0(
#365
b100 >
1(
#370
0(
#375
b100 0
b1010 '
b101 >
1"
1(
#380
0(
#385
b110 >
1(
#390
0(
#395
b111 >
1(
#400
0(
#405
b11 9
b0 >
1(
#410
0(
#415
1!
b1 >
0"
1;
1(
#420
0(
#425
b10 >
1(
#430
0(
#435
b11 >
1(
#440
0(
#445
b100 >
1(
#450
0(
#455
b101 0
b10101 '
b101 >
1"
1(
#460
0(
#465
b110 >
1(
#470
0(
#475
b111 >
1(
#480
0(
#485
b10 9
b0 >
1(
#490
0(
#495
0!
b1 >
0"
0;
1(
#500
0(
#505
b10 >
1(
#510
0(
#515
b11 >
1(
#520
0(
#525
b100 >
1(
#530
0(
#535
b110 0
b101010 '
b101 >
1"
1(
#540
0(
#545
b110 >
1(
#550
0(
#555
b111 >
1(
#560
0(
#565
b1 9
b0 >
1(
#570
0(
#575
1!
b1 >
0"
1;
1(
#580
0(
#585
b10 >
1(
#590
0(
#595
b11 >
1(
#600
0(
#605
b100 >
1(
#610
0(
#615
b111 0
b1010101 '
b101 >
1"
1(
#620
0(
#625
b110 >
1(
#630
0(
#635
b111 >
1(
#640
0(
#645
b0 9
b0 >
1(
#650
0(
#655
0!
b1 >
0"
0;
1(
#660
0(
#665
b10 >
1(
#670
0(
#675
b11 >
1(
#680
0(
#685
b100 >
1(
#690
0(
#695
b1000 0
b10101010 '
b101 >
1"
1(
#700
0(
#705
b110 >
1(
#710
0(
#715
b111 >
1(
#720
0(
#725
b11 =
b0 >
1(
#730
0(
#735
1&
1+
0!
b1 >
0"
0:
1(
#740
0(
#745
b10 >
1(
#750
0(
#755
b11 >
1(
#760
0(
#765
b100 >
1(
#770
0(
#775
b101 >
1"
1(
#780
0(
#785
b110 >
1(
#790
0(
#795
b111 >
1(
#800
0(
#805
0+
b100 =
0"
1:
b0 >
1(
#810
0(
#815
b1 >
1(
#820
0(
#825
b10 >
1(
#830
0(
#835
b11 >
1(
#840
0(
#845
b100 >
1(
#850
0(
#855
b101 >
1(
#860
0(
#865
b110 >
1(
#870
0(
#875
1!
b111 >
1;
1(
#880
0(
#885
b101 =
b0 >
1(
#890
0(
#895
b0 =
1#
0$
1(
#900
0(
#905
1"
0#
1(
