ratan/mux_project/mux2to1.v
module mux2to1(input I0,input I1,input S,output Y);
assign Y=S ? I1:I0;
endmodule

ratan/mux_project/mux4to1.v
module mux4to1(input I0,input I1,input I2,input I3,input S0,input S1,output Y);
wire W0,W1;
mux2to1 MUX0(.I0(I0), .I1(I1), .S(S0), .Y(W0));
mux2to1 MUX1(.I0(I2), .I1(I3), .S(S0), .Y(W1));
mux2to1 MUX2(.I0(W0), .I1(W1), .S(S1), .Y(Y));
endmodule

ratan/mux_project/mux8to1.v
module mux8to1(input I0,input I1,input I2,input I3,input I4,input I5,input I6,input I7,input S0,input S1,input S2,output Y);
wire W0,W1;
mux4to1 MUX0(.I0(I0), .I1(I1), .I2(I2), .I3(I3), .S0(S0), .S1(S1), .Y(W0));
mux4to1 MUX1(.I0(I4), .I1(I5), .I2(I6), .I3(I7), .S0(S0), .S1(S1), .Y(W1));
mux2to1 MUX2(.I0(W0), .I1(W1), .S(S2), .Y(Y));
endmodule

ratan/mux_project/mux8to1_tb.v
module mux8to1_tb;
reg I0,I1,I2,I3;
reg I4,I5,I6,I7;
reg S0,S1,S2;
wire Y;
mux8to1 DUT(.I0(I0), .I1(I1), .I3(I3), .I4(I4), .I5(I5), .I6(I6), .I7(I7), .S0(S0), .S1(S1), .S2(S2), .Y(Y));
initial begin
	$dumpfile("mux8to1.vcd");
	$dumpvars(0,mux8to1_tb);
	I0=0;
	I1=1;
	I2=0;
	I3=1;
	I4=0;
	I5=1;
	I6=0;
	I7=1;
	S2=0; S1=0; S0=0;
	#10;
	S2=0; S1=0; S0=1;
        #10;
	S2=0; S1=1; S0=0;
        #10;
	S2=0; S1=1; S0=1;
        #10;
	S2=1; S1=0; S0=0;
        #10;
	S2=1; S1=0; S0=1;
        #10;
	S2=1; S1=1; S0=0;
        #10;
	S2=1; S1=1; S0=1;
        #10;
	$finish;
end
endmodule

ratan/mux_project/mux8to1.vcd
$date
	Mon Aug 31 07:34:49 2026
$end
$version
	Icarus Verilog
$end
$timescale
	1s
$end
$scope module mux8to1_tb $end
$var wire 1 ! Y $end
$var reg 1 " I0 $end
$var reg 1 # I1 $end
$var reg 1 $ I2 $end
$var reg 1 % I3 $end
$var reg 1 & I4 $end
$var reg 1 ' I5 $end
$var reg 1 ( I6 $end
$var reg 1 ) I7 $end
$var reg 1 * S0 $end
$var reg 1 + S1 $end
$var reg 1 , S2 $end
$scope module DUT $end
$var wire 1 " I0 $end
$var wire 1 # I1 $end
$var wire 1 - I2 $end
$var wire 1 % I3 $end
$var wire 1 & I4 $end
$var wire 1 ' I5 $end
$var wire 1 ( I6 $end
$var wire 1 ) I7 $end
$var wire 1 * S0 $end
$var wire 1 + S1 $end
$var wire 1 , S2 $end
$var wire 1 ! Y $end
$var wire 1 . W1 $end
$var wire 1 / W0 $end
$scope module MUX0 $end
$var wire 1 " I0 $end
$var wire 1 # I1 $end
$var wire 1 - I2 $end
$var wire 1 % I3 $end
$var wire 1 * S0 $end
$var wire 1 + S1 $end
$var wire 1 / Y $end
$var wire 1 0 W1 $end
$var wire 1 1 W0 $end
$scope module MUX0 $end
$var wire 1 " I0 $end
$var wire 1 # I1 $end
$var wire 1 * S $end
$var wire 1 1 Y $end
$upscope $end
$scope module MUX1 $end
$var wire 1 - I0 $end
$var wire 1 % I1 $end
$var wire 1 * S $end
$var wire 1 0 Y $end
$upscope $end
$scope module MUX2 $end
$var wire 1 1 I0 $end
$var wire 1 0 I1 $end
$var wire 1 + S $end
$var wire 1 / Y $end
$upscope $end
$upscope $end
$scope module MUX1 $end
$var wire 1 & I0 $end
$var wire 1 ' I1 $end
$var wire 1 ( I2 $end
$var wire 1 ) I3 $end
$var wire 1 * S0 $end
$var wire 1 + S1 $end
$var wire 1 . Y $end
$var wire 1 2 W1 $end
$var wire 1 3 W0 $end
$scope module MUX0 $end
$var wire 1 & I0 $end
$var wire 1 ' I1 $end
$var wire 1 * S $end
$var wire 1 3 Y $end
$upscope $end
$scope module MUX1 $end
$var wire 1 ( I0 $end
$var wire 1 ) I1 $end
$var wire 1 * S $end
$var wire 1 2 Y $end
$upscope $end
$scope module MUX2 $end
$var wire 1 3 I0 $end
$var wire 1 2 I1 $end
$var wire 1 + S $end
$var wire 1 . Y $end
$upscope $end
$upscope $end
$scope module MUX2 $end
$var wire 1 / I0 $end
$var wire 1 . I1 $end
$var wire 1 , S $end
$var wire 1 ! Y $end
$upscope $end
$upscope $end
$upscope $end
$enddefinitions $end
$comment Show the parameter values. $end
$dumpall
$end
#0
$dumpvars
03
02
01
z0
0/
0.
z-
0,
0+
0*
1)
0(
1'
0&
1%
0$
1#
0"
0!
$end
#10
1!
1/
1.
11
10
13
12
1*
#20
z!
z/
0.
01
z0
03
02
0*
1+
#30
1!
1/
1.
11
10
13
12
1*
#40
0!
0/
0.
01
z0
03
02
0*
0+
1,
#50
1!
1/
1.
11
10
13
12
1*
#60
0!
z/
0.
01
z0
03
02
0*
1+
#70
1!
1/
1.
11
10
13
12
1*
