mamatha/dff/dff.v
module dff(
	input D,
	input clk,
	input set,
	input reset,
	output reg q);

always @(posedge clk or posedge set or posedge reset)
begin
	if(reset)
	q<=1'b0;
	else if(set)
	q<=1'b1;
	else
	q<=D;
end
endmodule

mamatha/dff_tb.v
module dff_tb;
reg D,clk,set,reset;
wire q;
dff uut(.D(D),
.clk(clk),
.set(set),
.reset(reset),
.q(q));
always 
#5 clk=~clk;
initial
begin
$dumpfile("dff.vcd");
$dumpvars(0,dff_tb);
clk=0;
D=0;
set=0;
reset=0;
#10 D=1;
#10 D=0;
#10 set=1;
#10 set=0;
#10 reset=1;
#10 reset=0;
#10 D=1;
#10 $finish;
end
initial
begin
$monitor("Time=%0t | D=%b | clk=%b | q=%b | SET=%b | RESET=%b",$time,D,clk,q,set,reset);
end
endmodule

mamatha/dff/dff.vcd
$date
	Thu Aug 27 07:58:43 2026
$end
$version
	Icarus Verilog
$end
$timescale
	1s
$end
$scope module dff_tb $end
$var wire 1 ! q $end
$var reg 1 " D $end
$var reg 1 # clk $end
$var reg 1 $ reset $end
$var reg 1 % set $end
$scope module uut $end
$var wire 1 " D $end
$var wire 1 # clk $end
$var wire 1 $ reset $end
$var wire 1 % set $end
$var reg 1 ! q $end
$upscope $end
$upscope $end
$enddefinitions $end
$comment Show the parameter values. $end
$dumpall
$end
#0
$dumpvars
0%
0$
0#
0"
x!
$end
#5
0!
1#
#10
0#
1"
#15
1!
1#
#20
0#
0"
#25
0!
1#
#30
1!
0#
1%
#35
1#
#40
0#
0%
#45
0!
1#
#50
0#
1$
#55
1#
#60
0#
0$
#65
1#
#70
0#
1"
#75
1!
1#
