karthik/Digital/I2C/i2c_master_fsm.v
module i2c_master_fsm (
    input wire clk,
    input wire reset,
    input wire start_transfer,
    input wire rw_flag,        // 0 = Write, 1 = Read
    input wire ack_in,         // Acknowledgment from slave
    output reg gen_start,
    output reg gen_stop,
    output reg tx_enable,
    output reg rx_enable,
    output wire [2:0] current_state
);
    localparam IDLE      = 3'b000;
    localparam START     = 3'b001;
    localparam ADDRESS   = 3'b010;
    localparam ACK_ADDR  = 3'b011;
    localparam DATA      = 3'b100;
    localparam ACK_DATA  = 3'b101;
    localparam STOP      = 3'b110;

    reg [2:0] state, next_state;
    reg [3:0] bit_count;

    assign current_state = state;
    
    always @(posedge clk or posedge reset) begin
        if (reset) begin
            state <= IDLE;
            bit_count <= 4'd0;
        end else begin
            state <= next_state;
            
            
            if (state == ADDRESS || state == DATA)
                bit_count <= bit_count + 1'b1;
            else
                bit_count <= 4'd0;
        end
    end

  
    always @(*) begin
       
        next_state = state;
        gen_start  = 1'b0;
        gen_stop   = 1'b0;
        tx_enable  = 1'b0;
        rx_enable  = 1'b0;

        case (state)
            IDLE: begin
                if (start_transfer) begin
                    gen_start = 1'b1;
                    next_state = START;
                end
            end
            
            START: begin
                next_state = ADDRESS;
            end
            
            ADDRESS: begin
                tx_enable = 1'b1;
                if (bit_count == 4'd7)
                    next_state = ACK_ADDR;
            end
            
            ACK_ADDR: begin
                next_state = DATA; 
            end
            
            DATA: begin
              
                if (rw_flag == 1'b0)
                    tx_enable = 1'b1;
                else
                    rx_enable = 1'b1;
                    
                if (bit_count == 4'd7)
                    next_state = ACK_DATA;
            end
            
            ACK_DATA: begin
                next_state = STOP;
            end
            
            STOP: begin
                gen_stop = 1'b1;
                next_state = IDLE;
            end
            
            default: next_state = IDLE;
        endcase
    end
endmodule

karthik/Digital/I2C/tb_i2c_master_fsm.v
`timescale 1ns / 1ps

module tb_i2c_master_fsm;

    // Inputs
    reg clk;
    reg reset;
    reg start_transfer;
    reg rw_flag;
    reg ack_in;

    // Outputs
    wire gen_start;
    wire gen_stop;
    wire tx_enable;
    wire rx_enable;
    wire [2:0] current_state;

    i2c_master_fsm uut (
        .clk(clk),
        .reset(reset),
        .start_transfer(start_transfer),
        .rw_flag(rw_flag),
        .ack_in(ack_in),
        .gen_start(gen_start),
        .gen_stop(gen_stop),
        .tx_enable(tx_enable),
        .rx_enable(rx_enable),
        .current_state(current_state)
    );

    always #5 clk = ~clk;

    initial begin
        
        $dumpfile("i2c_fsm.vcd");
        $dumpvars(0, tb_i2c_master_fsm);

        
        clk = 0;
        reset = 1;
        start_transfer = 0;
        rw_flag = 0;
        ack_in = 0;

        #20;
        reset = 0;
        #10;

        // case 1: I2C Write
        $display("\n--- Starting I2C WRITE Transaction ---");
        rw_flag = 0;
        start_transfer = 1;
        #10;
        start_transfer = 0;

        #200; 
        // case 2: I2C Read
        $display("\n--- Starting I2C READ Transaction ---");
        rw_flag = 1;           // 1 means Read
        start_transfer = 1;    // Trigger the FSM
        #10;
        start_transfer = 0;

        // Wait for clock cycle to finish
        #200;

        $display("\nSimulation Complete.");
        $finish;
    end

    // Print State Changes to the Terminal
    always @(current_state) begin
        case(current_state)
            3'b000: $display("Time: %0t | State: IDLE", $time);
            3'b001: $display("Time: %0t | State: START", $time);
            3'b010: $display("Time: %0t | State: ADDRESS", $time);
            3'b011: $display("Time: %0t | State: ACK_ADDR", $time);
            3'b100: $display("Time: %0t | State: DATA", $time);
            3'b101: $display("Time: %0t | State: ACK_DATA", $time);
            3'b110: $display("Time: %0t | State: STOP", $time);
        endcase
    end

endmodule

karthik/I2C/i2c_fsm.vcd
$date
	Wed Sep  2 04:13:37 2026
$end
$version
	Icarus Verilog
$end
$timescale
	1ps
$end
$scope module tb_i2c_master_fsm $end
$var wire 1 ! tx_enable $end
$var wire 1 " rx_enable $end
$var wire 1 # gen_stop $end
$var wire 1 $ gen_start $end
$var wire 3 % current_state [2:0] $end
$var reg 1 & ack_in $end
$var reg 1 ' clk $end
$var reg 1 ( reset $end
$var reg 1 ) rw_flag $end
$var reg 1 * start_transfer $end
$scope module uut $end
$var wire 1 & ack_in $end
$var wire 1 ' clk $end
$var wire 3 + current_state [2:0] $end
$var wire 1 ( reset $end
$var wire 1 ) rw_flag $end
$var wire 1 * start_transfer $end
$var parameter 3 , ACK_ADDR $end
$var parameter 3 - ACK_DATA $end
$var parameter 3 . ADDRESS $end
$var parameter 3 / DATA $end
$var parameter 3 0 IDLE $end
$var parameter 3 1 START $end
$var parameter 3 2 STOP $end
$var reg 4 3 bit_count [3:0] $end
$var reg 1 $ gen_start $end
$var reg 1 # gen_stop $end
$var reg 3 4 next_state [2:0] $end
$var reg 1 " rx_enable $end
$var reg 3 5 state [2:0] $end
$var reg 1 ! tx_enable $end
$upscope $end
$upscope $end
$enddefinitions $end
$comment Show the parameter values. $end
$dumpall
b110 2
b1 1
b0 0
b100 /
b10 .
b101 -
b11 ,
$end
#0
$dumpvars
b0 5
b0 4
b0 3
b0 +
0*
0)
1(
0'
0&
b0 %
0$
0#
0"
0!
$end
#5000
1'
#10000
0'
#15000
1'
#20000
0'
0(
#25000
1'
#30000
b1 4
1$
0'
1*
#35000
b10 4
0$
b1 %
b1 +
b1 5
1'
#40000
b10 4
0'
0*
#45000
1!
b10 %
b10 +
b10 5
1'
#50000
0'
#55000
1!
b1 3
1'
#60000
0'
#65000
1!
b10 3
1'
#70000
0'
#75000
1!
b11 3
1'
#80000
0'
#85000
1!
b100 3
1'
#90000
0'
#95000
1!
b101 3
1'
#100000
0'
#105000
1!
b110 3
1'
#110000
0'
#115000
b11 4
1!
b111 3
1'
#120000
0'
#125000
b100 4
0!
b1000 3
b11 %
b11 +
b11 5
1'
#130000
0'
#135000
1!
b0 3
b100 %
b100 +
b100 5
1'
#140000
0'
#145000
1!
b1 3
1'
#150000
0'
#155000
1!
b10 3
1'
#160000
0'
#165000
1!
b11 3
1'
#170000
0'
#175000
1!
b100 3
1'
#180000
0'
#185000
1!
b101 3
1'
#190000
0'
#195000
1!
b110 3
1'
#200000
0'
#205000
b101 4
1!
b111 3
1'
#210000
0'
#215000
b110 4
0!
b1000 3
b101 %
b101 +
b101 5
1'
#220000
0'
#225000
b0 4
1#
b0 3
b110 %
b110 +
b110 5
1'
#230000
0'
#235000
0#
b0 %
b0 +
b0 5
1'
#240000
b1 4
1$
0'
1*
1)
#245000
b10 4
0$
b1 %
b1 +
b1 5
1'
#250000
b10 4
0'
0*
#255000
1!
b10 %
b10 +
b10 5
1'
#260000
0'
#265000
1!
b1 3
1'
#270000
0'
#275000
1!
b10 3
1'
#280000
0'
#285000
1!
b11 3
1'
#290000
0'
#295000
1!
b100 3
1'
#300000
0'
#305000
1!
b101 3
1'
#310000
0'
#315000
1!
b110 3
1'
#320000
0'
#325000
b11 4
1!
b111 3
1'
#330000
0'
#335000
b100 4
0!
b1000 3
b11 %
b11 +
b11 5
1'
#340000
0'
#345000
1"
b0 3
b100 %
b100 +
b100 5
1'
#350000
0'
#355000
1"
b1 3
1'
#360000
0'
#365000
1"
b10 3
1'
#370000
0'
#375000
1"
b11 3
1'
#380000
0'
#385000
1"
b100 3
1'
#390000
0'
#395000
1"
b101 3
1'
#400000
0'
#405000
1"
b110 3
1'
#410000
0'
#415000
b101 4
1"
b111 3
1'
#420000
0'
#425000
b110 4
0"
b1000 3
b101 %
b101 +
b101 5
1'
#430000
0'
#435000
b0 4
1#
b0 3
b110 %
b110 +
b110 5
1'
#440000
0'
#445000
0#
b0 %
b0 +
b0 5
1'
