mamatha/full_subtractor/full_subtractor.v
module full_subtractor(a,b,bin,diff,bout);
input a,b,bin;
output diff,bout;
assign diff=a^b^bin;
assign bout=(~a&b)|(~a&bin)|(b&bin);
endmodule

mamatha/full_subtractor/full_subtractor_tb.v
module full_subtractor_tb;
reg a,b,bin;
wire diff,bout;
full_subtractor uut(
.a(a),
.b(b),
.bin(bin),
.diff(diff),
.bout(bout)
);

initial
begin
$dumpfile("full_subtractor.vcd");
$dumpvars(0,full_subtractor_tb);
$monitor("a=%b b=%b bin=%b diff=%b bout=%b",a,b,bin,diff,bout);

a=0;b=0;bin=0;#10;
a=0;b=0;bin=1;#10;
a=0;b=1;bin=0;#10;
a=0;b=1;bin=1;#10;
a=1;b=0;bin=0;#10;
a=1;b=0;bin=1;#10;
a=1;b=1;bin=0;#10;
a=1;b=1;bin=1;#10;

$finish;
end
endmodule

mamatha/full_subtractor/full_subtractor.vcd
$date
	Thu Aug 27 05:37:04 2026
$end
$version
	Icarus Verilog
$end
$timescale
	1s
$end
$scope module full_subtractor_tb $end
$var wire 1 ! diff $end
$var wire 1 " bout $end
$var reg 1 # a $end
$var reg 1 $ b $end
$var reg 1 % bin $end
$scope module uut $end
$var wire 1 # a $end
$var wire 1 $ b $end
$var wire 1 % bin $end
$var wire 1 " bout $end
$var wire 1 ! diff $end
$upscope $end
$upscope $end
$enddefinitions $end
$comment Show the parameter values. $end
$dumpall
$end
#0
$dumpvars
0%
0$
0#
0"
0!
$end
#10
1"
1!
1%
#20
0%
1$
#30
0!
1%
#40
0"
1!
0%
0$
1#
#50
0!
1%
#60
0%
1$
#70
1"
1!
1%
