laxmi/i2c_master_tx.v
module i2c_master_tx(input wire clk,input wire rst_n,
input wire tx_start,input wire[7:0] tx_data,
input wire scl,output wire sda,
output reg tx_busy,output reg tx_done);
 reg [7:0] tx_shift_reg;

reg [7:0] bit_count;
reg sda_drive_low;
assign sda=sda_drive_low?1'b0:1'bz;

always @(posedge scl or negedge rst_n) begin
if(!rst_n) begin
tx_shift_reg <=8'h00;
bit_count <=4'd0;
tx_busy <=1'b0;
tx_done <=1'b0;
sda_drive_low <=1'b0;
end
else begin
tx_done<=1'b0;

if(tx_start && !tx_busy)
begin
tx_shift_reg <=tx_data;
bit_count <=4'd0;
tx_busy<=1'b1;
if(tx_data[7]==1'b0)
sda_drive_low<=1'b1;
else
sda_drive_low<=1'b0;
end
else if(tx_busy) begin
if(bit_count <4'd7)
begin
tx_shift_reg<={tx_shift_reg[6:0],1'b0};
bit_count<=bit_count+1'b1;
if(tx_shift_reg[6]==1'b0)
sda_drive_low<=1'b1;
else
sda_drive_low<=1'b0;
end
else begin
tx_busy<=1'b0;
tx_done<=1'b1;
bit_count<=4'd0;
sda_drive_low<=1'b0;
end
end
end
end
endmodule

laxmi/i2c_master_tx_tb.v
module i2c_master_tx_tb;
reg clk;
reg rst_n;
reg tx_start;
reg [7:0] tx_data;
reg scl;
wire sda;
wire tx_busy;
wire tx_done;
i2c_master_tx dut(
.clk(clk),
.rst_n(rst_n),
.tx_start(tx_start),
.tx_data(tx_data),
.scl(scl),
.sda(sda),
.tx_busy(tx_busy),
.tx_done(tx_done)
);
pullup(sda);
initial
begin
clk=1'b0;
forever #5 clk=~clk;
end
initial
begin
scl=1'b1;
forever begin
#10 scl=1'b0;
#10 scl=1'b1;
end
end

initial begin
$dumpfile("i2c_master_tx.vcd");
$dumpvars(0,i2c_master_tx_tb);

rst_n=1'b0;
tx_start=1'b0;
tx_data=8'h00;
#25;
rst_n=1'b1;
@(negedge scl);
tx_data =8'hA5;
tx_start=1'b1;
@(negedge scl);
tx_start=1'b0;
wait(tx_done);
#20;

$display("------------------------");
$display("First transmission completed");
$display("TX DATA=0x%02h",tx_data);
$display("------------------------");
#20;
$finish;
end
always@(posedge scl) begin
if(tx_busy) begin
$display("TIME=%-t SDA=%b SHIFT_REG=%b BIT_COUNT=%0d",
$time,sda,dut.tx_shift_reg,dut.bit_count);
end
end
endmodule

laxmi/i2c_master_tx.vcd
$date
	Wed Sep  2 04:54:54 2026
$end
$version
	Icarus Verilog
$end
$timescale
	1s
$end
$scope module i2c_master_tx_tb $end
$var wire 1 ! sda $end
$var wire 1 " tx_done $end
$var wire 1 # tx_busy $end
$var reg 1 $ clk $end
$var reg 1 % rst_n $end
$var reg 1 & scl $end
$var reg 8 ' tx_data [7:0] $end
$var reg 1 ( tx_start $end
$scope module dut $end
$var wire 1 $ clk $end
$var wire 1 % rst_n $end
$var wire 1 & scl $end
$var wire 1 ! sda $end
$var wire 8 ) tx_data [7:0] $end
$var wire 1 ( tx_start $end
$var reg 8 * bit_count [7:0] $end
$var reg 1 + sda_drive_low $end
$var reg 1 # tx_busy $end
$var reg 1 " tx_done $end
$var reg 8 , tx_shift_reg [7:0] $end
$upscope $end
$upscope $end
$enddefinitions $end
$comment Show the parameter values. $end
$dumpall
$end
#0
$dumpvars
b0 ,
0+
b0 *
b0 )
0(
b0 '
1&
0%
0$
0#
0"
1!
$end
#5
1$
#10
0$
0&
#15
1$
#20
0$
1&
#25
1$
1%
#30
1(
b10100101 '
b10100101 )
0$
0&
#35
1$
#40
1#
b10100101 ,
0$
1&
#45
1$
#50
0(
0$
0&
#55
1$
#60
0!
1+
b1 *
b1001010 ,
0$
1&
#65
1$
#70
0$
0&
#75
1$
#80
1!
0+
b10 *
b10010100 ,
0$
1&
#85
1$
#90
0$
0&
#95
1$
#100
0!
1+
b11 *
b101000 ,
0$
1&
#105
1$
#110
0$
0&
#115
1$
#120
b100 *
b1010000 ,
0$
1&
#125
1$
#130
0$
0&
#135
1$
#140
1!
0+
b101 *
b10100000 ,
0$
1&
#145
1$
#150
0$
0&
#155
1$
#160
0!
1+
b110 *
b1000000 ,
0$
1&
#165
1$
#170
0$
0&
#175
1$
#180
1!
0+
b111 *
b10000000 ,
0$
1&
#185
1$
#190
0$
0&
#195
1$
#200
b0 *
1"
0#
0$
1&
#205
1$
#210
0$
0&
#215
1$
#220
0"
0$
1&
#225
1$
#230
0$
0&
#235
1$
#240
0$
1&
