nanditha/half_adder.v
module half_adder(
input A,
input B,
output SUM,
output CARRY
);
assign SUM = A^B;
assign CARRY = A&B;
endmodule

nanditha/full_adder.v
module full_adder(
input A,
input B,
input Cin,
output Sum,
output Carry
);
wire S1;
wire C1;
wire C2;
half_adder HA1(
.A(A),
.B(B),
.SUM(S1),
.CARRY(C1)
);
half_adder HA2(
.A(S1),
.B(Cin),
.SUM(Sum),
.CARRY(C2)
);
assign Carry = C1|C2;
endmodule

nanditha/full_addertb.v
`timescale 1ns/1ps
module full_addertb;
reg A,B,Cin;
wire Sum,Cout;
full_adder uut(
.A(A),
.B(B),
.Cin(Cin),
.Sum(Sum),
.Carry(Cout)
);

initial begin
$dumpfile("full_adder.vcd");
$dumpvars(0, full_addertb);

A = 0; B = 0; Cin = 0;
#10 A = 0; B = 0; Cin = 1;
#10 A = 0; B = 1; Cin = 0;
#10 A = 0; B = 1; Cin = 1;
#10 A = 1; B = 0; Cin = 0;
#10 A = 1; B = 0; Cin = 1;
#10 A = 1; B = 1; Cin = 0;
#10 A = 1; B = 1; Cin = 1;
end
endmodule

nanditha/full_adder.vcd
$date
	Thu Aug 27 09:39:15 2026
$end
$version
	Icarus Verilog
$end
$timescale
	1ps
$end
$scope module full_addertb $end
$var wire 1 ! Sum $end
$var wire 1 " Cout $end
$var reg 1 # A $end
$var reg 1 $ B $end
$var reg 1 % Cin $end
$scope module uut $end
$var wire 1 # A $end
$var wire 1 $ B $end
$var wire 1 " Carry $end
$var wire 1 % Cin $end
$var wire 1 ! Sum $end
$var wire 1 & S1 $end
$var wire 1 ' C2 $end
$var wire 1 ( C1 $end
$scope module HA1 $end
$var wire 1 # A $end
$var wire 1 $ B $end
$var wire 1 ( CARRY $end
$var wire 1 & SUM $end
$upscope $end
$scope module HA2 $end
$var wire 1 & A $end
$var wire 1 % B $end
$var wire 1 ' CARRY $end
$var wire 1 ! SUM $end
$upscope $end
$upscope $end
$upscope $end
$enddefinitions $end
$comment Show the parameter values. $end
$dumpall
$end
#0
$dumpvars
0(
0'
0&
0%
0$
0#
0"
0!
$end
#10000
1!
1%
#20000
1&
0%
1$
#30000
1"
0!
1'
1%
#40000
0"
1!
0'
0%
0$
1#
#50000
1"
0!
1'
1%
#60000
0'
0&
1(
0%
1$
#70000
1!
1%
