jahanavi/counter.v
module counter(
input clk,
input reset,
output reg [3:0] count
);

always @(posedge clk) begin
if (reset)
count <= 4'b0000;
else
count <= count + 1'b1;
end
endmodule

jahanavi/counter_tb.v
module counter_tb;
reg clk;
reg reset;
wire [3:0] count;

counter c1(
.clk(clk),
.reset(reset),
.count(count)
);

initial begin
$dumpfile("counter.vcd");
$dumpvars(0, counter_tb);

clk =0;
reset =1;
#10;
reset =0;
#100;
$finish;
end
always #5 clk = ~clk;
endmodule

jahanavi/counter.vcd
$date
	Mon Aug 31 09:30:50 2026
$end
$version
	Icarus Verilog
$end
$timescale
	1s
$end
$scope module counter_tb $end
$var wire 4 ! count [3:0] $end
$var reg 1 " clk $end
$var reg 1 # reset $end
$scope module c1 $end
$var wire 1 " clk $end
$var wire 1 # reset $end
$var reg 4 $ count [3:0] $end
$upscope $end
$upscope $end
$enddefinitions $end
$comment Show the parameter values. $end
$dumpall
$end
#0
$dumpvars
bx $
1#
0"
bx !
$end
#5
b0 !
b0 $
1"
#10
0"
0#
#15
b1 !
b1 $
1"
#20
0"
#25
b10 !
b10 $
1"
#30
0"
#35
b11 !
b11 $
1"
#40
0"
#45
b100 !
b100 $
1"
#50
0"
#55
b101 !
b101 $
1"
#60
0"
#65
b110 !
b110 $
1"
#70
0"
#75
b111 !
b111 $
1"
#80
0"
#85
b1000 !
b1000 $
1"
#90
0"
#95
b1001 !
b1001 $
1"
#100
0"
#105
b1010 !
b1010 $
1"
