jahanavi/d1.v
module decoder_1to2(
input a,
input en,
output [1:0] y
);

assign y[0] = en & ~a;
assign y[1] = en & a;

endmodule

jahanavi/d2.v
module decoder_2to4(
input [1:0] a,
input en,
output [3:0] y
);
wire [1:0] w;
decoder_1to2 d0(a[1], en, w);
decoder_1to2 d1(a[0], w[0], y[1:0]);
decoder_1to2 d2(a[0], w[1], y[3:2]);
endmodule

jahanavi/d3.v
module decoder_3to8(
input [2:0] a,
input en,
output [7:0] y
);
wire [3:0] w;
decoder_2to4 d0(a[2:1],en,w);
assign y[0] = w[0] & ~a[0];
assign y[1] = w[0] & a[0];

assign y[2] = w[1] & ~a[0];
assign y[3] = w[1] & a[0];

assign y[4] = w[2] & ~a[0];
assign y[5] = w[2] & a[0];

assign y[6] = w[3] & ~a[0];
assign y[7] = w[3] & a[0];
endmodule

jahanavi/d3_tb.v
module tb3;
reg [2:0] a;
reg en;
wire [7:0]y;
decoder_3to8 d3(a,en,y);
initial begin
$dumpfile("d3.vcd");
$dumpvars(0, tb3);
en=0; a=3'b000; #10;
en=1; a=3'b000; #10;
en=1; a=3'b001; #10;
en=1; a=3'b010; #10;
en=1; a=3'b011; #10;
en=1; a=3'b100; #10;
en=1; a=3'b101; #10;
en=1; a=3'b110; #10;
en=1; a=3'b111; #10;
$finish;
end
endmodule

jahanavi/d3.vcd
$date
	Fri Aug 28 05:28:14 2026
$end
$version
	Icarus Verilog
$end
$timescale
	1s
$end
$scope module tb3 $end
$var wire 8 ! y [7:0] $end
$var reg 3 " a [2:0] $end
$var reg 1 # en $end
$scope module d3 $end
$var wire 3 $ a [2:0] $end
$var wire 1 # en $end
$var wire 8 % y [7:0] $end
$var wire 4 & w [3:0] $end
$scope module d0 $end
$var wire 2 ' a [1:0] $end
$var wire 1 # en $end
$var wire 4 ( y [3:0] $end
$var wire 2 ) w [1:0] $end
$scope module d0 $end
$var wire 1 * a $end
$var wire 1 # en $end
$var wire 2 + y [1:0] $end
$upscope $end
$scope module d1 $end
$var wire 1 , a $end
$var wire 1 - en $end
$var wire 2 . y [1:0] $end
$upscope $end
$scope module d2 $end
$var wire 1 / a $end
$var wire 1 0 en $end
$var wire 2 1 y [1:0] $end
$upscope $end
$upscope $end
$upscope $end
$upscope $end
$enddefinitions $end
$comment Show the parameter values. $end
$dumpall
$end
#0
$dumpvars
b0 1
00
0/
b0 .
0-
0,
b0 +
0*
b0 )
b0 (
b0 '
b0 &
b0 %
b0 $
0#
b0 "
b0 !
$end
#10
b1 !
b1 %
b1 &
b1 (
b1 .
1-
b1 )
b1 +
1#
#20
b10 !
b10 %
b1 "
b1 $
#30
b10 &
b10 (
b10 .
1,
1/
b100 !
b100 %
b1 '
b10 "
b10 $
#40
b1000 !
b1000 %
b11 "
b11 $
#50
0-
b1 1
10
b10 )
b10 +
b100 &
b100 (
b0 .
1*
0,
0/
b10000 !
b10000 %
b10 '
b100 "
b100 $
#60
b100000 !
b100000 %
b101 "
b101 $
#70
b1000 &
b1000 (
b10 1
1,
1/
b1000000 !
b1000000 %
b11 '
b110 "
b110 $
#80
b10000000 !
b10000000 %
b111 "
b111 $
